petit_kernel/__init__.py
petit_kernel/ops.cpython-312-x86_64-linux-gnu.so
petit_kernel-0.0.2.dist-info/METADATA
petit_kernel-0.0.2.dist-info/WHEEL
petit_kernel-0.0.2.dist-info/top_level.txt
petit_kernel-0.0.2.dist-info/RECORD
petit_kernel-0.0.2.dist-info/licenses/LICENSE.txt
