Metadata-Version: 2.4
Name: petit_kernel
Version: 0.0.2
Summary: Optimized FP4 GPU kernels for AMD GPUs
Author-email: Haohui Mai <haohui@causalflow.ai>
Maintainer-email: Haohui Mai <haohui@causalflow.ai>
Project-URL: Homepage, https://github.com/causalflow-ai/petit-kernel
Classifier: Programming Language :: Python :: 3.8
Classifier: Programming Language :: Python :: 3.9
Classifier: Programming Language :: Python :: 3.10
Classifier: Programming Language :: Python :: 3.11
Classifier: Programming Language :: Python :: 3.12
Classifier: License :: OSI Approved :: Apache Software License
Classifier: Topic :: Scientific/Engineering :: Artificial Intelligence
Classifier: Operating System :: OS Independent
License-File: LICENSE.txt
Dynamic: license-file
